bamboo_engine/__init__.py
bamboo_engine/__version__.py
bamboo_engine/api.py
bamboo_engine/builder/__init__.py
bamboo_engine/builder/builder.py
bamboo_engine/builder/flow/__init__.py
bamboo_engine/builder/flow/activity.py
bamboo_engine/builder/flow/base.py
bamboo_engine/builder/flow/data.py
bamboo_engine/builder/flow/event.py
bamboo_engine/builder/flow/gateway.py
bamboo_engine/config.py
bamboo_engine/context.py
bamboo_engine/engine.py
bamboo_engine/eri/__init__.py
bamboo_engine/eri/interfaces.py
bamboo_engine/eri/models/__init__.py
bamboo_engine/eri/models/event.py
bamboo_engine/eri/models/handler.py
bamboo_engine/eri/models/interrupt.py
bamboo_engine/eri/models/node.py
bamboo_engine/eri/models/runtime.py
bamboo_engine/exceptions.py
bamboo_engine/handler.py
bamboo_engine/handlers/__init__.py
bamboo_engine/handlers/conditional_parallel_gateway.py
bamboo_engine/handlers/converge_gateway.py
bamboo_engine/handlers/empty_end_event.py
bamboo_engine/handlers/empty_start_event.py
bamboo_engine/handlers/exclusive_gateway.py
bamboo_engine/handlers/executable_end_event.py
bamboo_engine/handlers/parallel_gateway.py
bamboo_engine/handlers/service_activity.py
bamboo_engine/handlers/subprocess.py
bamboo_engine/interrupt.py
bamboo_engine/local.py
bamboo_engine/metrics.py
bamboo_engine/states.py
bamboo_engine/template/__init__.py
bamboo_engine/template/sandbox.py
bamboo_engine/template/template.py
bamboo_engine/utils/__init__.py
bamboo_engine/utils/boolrule/__init__.py
bamboo_engine/utils/boolrule/boolrule.py
bamboo_engine/utils/collections.py
bamboo_engine/utils/constants.py
bamboo_engine/utils/expr.py
bamboo_engine/utils/graph.py
bamboo_engine/utils/host.py
bamboo_engine/utils/mako_safety.py
bamboo_engine/utils/mako_utils/__init__.py
bamboo_engine/utils/mako_utils/checker.py
bamboo_engine/utils/mako_utils/code_extract.py
bamboo_engine/utils/mako_utils/exceptions.py
bamboo_engine/utils/mako_utils/visitors.py
bamboo_engine/utils/object.py
bamboo_engine/utils/string.py
bamboo_engine-3.0.1.dist-info/LICENSE
bamboo_engine-3.0.1.dist-info/METADATA
bamboo_engine-3.0.1.dist-info/WHEEL
bamboo_engine-3.0.1.dist-info/RECORD
