Metadata-Version: 2.3
Name: bamboo-engine
Version: 3.0.1
Summary: Bamboo-engine is a general-purpose workflow engine
License: MIT
Author: homholueng
Author-email: homholueng@gmail.com
Requires-Python: >=3.11,<3.12
Classifier: License :: OSI Approved :: MIT License
Classifier: Programming Language :: Python :: 3
Classifier: Programming Language :: Python :: 3.11
Requires-Dist: Mako (>=1.3,<2.0)
Requires-Dist: Werkzeug (>=3,<4)
Requires-Dist: prometheus-client (>=0.20.0,<0.21.0)
Requires-Dist: pyparsing (>=3,<4)
